ott/__init__.py
ott/_version.py
ott/datasets.py
ott/py.typed
ott/types.py
ott/utils.py
ott/data/__init__.py
ott/data/_loaders.py
ott/experimental/__init__.py
ott/experimental/mmsinkhorn.py
ott/geometry/__init__.py
ott/geometry/costs.py
ott/geometry/distrib_costs.py
ott/geometry/epsilon_scheduler.py
ott/geometry/geodesic.py
ott/geometry/geometry.py
ott/geometry/graph.py
ott/geometry/grid.py
ott/geometry/low_rank.py
ott/geometry/pointcloud.py
ott/geometry/regularizers.py
ott/geometry/segment.py
ott/geometry/semidiscrete_pointcloud.py
ott/initializers/__init__.py
ott/initializers/linear/__init__.py
ott/initializers/linear/initializers.py
ott/initializers/linear/initializers_lr.py
ott/initializers/neural/__init__.py
ott/initializers/neural/meta_initializer.py
ott/initializers/quadratic/__init__.py
ott/initializers/quadratic/initializers.py
ott/math/__init__.py
ott/math/_lbfgs.py
ott/math/_legendre.py
ott/math/_velocity_from_brenier_potential.py
ott/math/fixed_point_loop.py
ott/math/matrix_square_root.py
ott/math/unbalanced_functions.py
ott/math/utils.py
ott/neural/__init__.py
ott/neural/data/__init__.py
ott/neural/data/ot_dataloader.py
ott/neural/data/semidiscrete_dataloader.py
ott/neural/methods/__init__.py
ott/neural/methods/expectile_neural_dual.py
ott/neural/methods/flow_matching.py
ott/neural/methods/monge_gap.py
ott/neural/methods/neuraldual.py
ott/neural/networks/__init__.py
ott/neural/networks/icnn.py
ott/neural/networks/potentials.py
ott/neural/networks/layers/__init__.py
ott/neural/networks/layers/conjugate.py
ott/neural/networks/layers/posdef.py
ott/neural/networks/velocity_field/__init__.py
ott/neural/networks/velocity_field/ema.py
ott/neural/networks/velocity_field/mlp.py
ott/neural/networks/velocity_field/unet.py
ott/problems/__init__.py
ott/problems/linear/__init__.py
ott/problems/linear/barycenter_problem.py
ott/problems/linear/linear_problem.py
ott/problems/linear/potentials.py
ott/problems/linear/semidiscrete_linear_problem.py
ott_jax-0.6.0.dist-info/licenses/LICENSE
ott_jax-0.6.0.dist-info/METADATA
ott_jax-0.6.0.dist-info/WHEEL
ott_jax-0.6.0.dist-info/top_level.txt
ott_jax-0.6.0.dist-info/RECORD
