Metadata-Version: 2.4
Name: ott-jax
Version: 0.6.0
Summary: Optimal Transport Tools in JAX
Author-email: OTT team <optimal.transport.tools@gmail.com>
License:                                  Apache License
Project-URL: Source Code, https://github.com/ott-jax/ott
Project-URL: Documentation, https://ott-jax.readthedocs.io
Project-URL: Issue Tracker, https://github.com/ott-jax/ott/issues
Project-URL: Changelog, https://github.com/ott-jax/ott/releases
Keywords: optimal transport,gromov wasserstein,sinkhorn,low-rank sinkhorn,sinkhorn divergences,wasserstein,wasserstein barycenter,jax,autodiff,implicit differentiation
Classifier: Typing :: Typed
Classifier: Development Status :: 4 - Beta
Classifier: License :: OSI Approved :: Apache Software License
Classifier: Topic :: Scientific/Engineering :: Mathematics
Classifier: Natural Language :: English
Classifier: Intended Audience :: Developers
Classifier: Intended Audience :: Science/Research
Classifier: Operating System :: POSIX :: Linux
Classifier: Operating System :: MacOS :: MacOS X
Classifier: Operating System :: Microsoft :: Windows
Classifier: Programming Language :: Python :: 3
Classifier: Programming Language :: Python :: 3.9
Classifier: Programming Language :: Python :: 3.10
Classifier: Programming Language :: Python :: 3.11
Classifier: Programming Language :: Python :: 3.12
Classifier: Programming Language :: Python :: 3.13
Requires-Python: >=3.9
License-File: LICENSE
Requires-Dist: jax>=0.4.0
Requires-Dist: jaxopt>=0.8
Requires-Dist: lineax>=0.0.7
Requires-Dist: numpy>=1.20.0
Requires-Dist: typing_extensions; python_version <= "3.9"
Requires-Dist: optax>=0.2.4
Provides-Extra: neural
Requires-Dist: flax>=0.6.6; extra == "neural"
Requires-Dist: optax>=0.2.4; extra == "neural"
Requires-Dist: diffrax>=0.4.1; extra == "neural"
Provides-Extra: dev
Requires-Dist: pre-commit>=2.16.0; extra == "dev"
Requires-Dist: tox>=4; extra == "dev"
Provides-Extra: test
Requires-Dist: pytest; extra == "test"
Requires-Dist: pytest-xdist; extra == "test"
Requires-Dist: pytest-cov; extra == "test"
Requires-Dist: pytest-memray; extra == "test"
Requires-Dist: coverage[toml]; extra == "test"
Requires-Dist: chex; extra == "test"
Requires-Dist: networkx>=2.5; extra == "test"
Requires-Dist: scikit-learn>=1.0; extra == "test"
Requires-Dist: tqdm; extra == "test"
Requires-Dist: tslearn>=0.5; python_version < "3.13" and extra == "test"
Requires-Dist: matplotlib; extra == "test"
Provides-Extra: docs
Requires-Dist: matplotlib; extra == "docs"
Requires-Dist: sphinx>=4.0; extra == "docs"
Requires-Dist: sphinx-book-theme>=1.0.1; extra == "docs"
Requires-Dist: sphinx_autodoc_typehints>=1.12.0; extra == "docs"
Requires-Dist: sphinx-copybutton>=0.5.1; extra == "docs"
Requires-Dist: sphinxcontrib-bibtex>=2.5.0; extra == "docs"
Requires-Dist: sphinxcontrib-spelling>=7.7.0; extra == "docs"
Requires-Dist: myst-nb>=0.17.1; extra == "docs"
Dynamic: license-file
